django_command_server.py
django_command_server-0.1.3.dist-info/licenses/LICENSE
django_command_server-0.1.3.dist-info/METADATA
django_command_server-0.1.3.dist-info/WHEEL
django_command_server-0.1.3.dist-info/top_level.txt
django_command_server-0.1.3.dist-info/RECORD
