Metadata-Version: 2.4
Name: django-command-server
Version: 0.1.3
Summary: Django management.command is running a long live task, we make it a linux daemon server, so that you can start, stop, restart the task.
Author: rRR0VrFP
Maintainer: rRR0VrFP
License: MIT
Keywords: django extentions
Classifier: Development Status :: 5 - Production/Stable
Classifier: Intended Audience :: Developers
Classifier: Topic :: Software Development :: Libraries :: Python Modules
Classifier: License :: OSI Approved :: MIT License
Classifier: Programming Language :: Python :: 3
Classifier: Programming Language :: Python :: 3 :: Only
License-File: LICENSE
Requires-Dist: django-click>=2.2.0
Requires-Dist: fastutils>=0.34.0
Requires-Dist: daemon-application>=0.2.1
Dynamic: author
Dynamic: classifier
Dynamic: description
Dynamic: description-content-type
Dynamic: keywords
Dynamic: license
Dynamic: license-file
Dynamic: maintainer
Dynamic: requires-dist
Dynamic: summary
